kalmantv/__init__.py
kalmantv/mv_gaussian.py
kalmantv/utils.py
kalmantv/cython/__init__.py
kalmantv/cython/_test.py
kalmantv/cython/blas.cp38-win_amd64.pyd
kalmantv/cython/blas.pxd
kalmantv/cython/kalmantv.cp38-win_amd64.pyd
kalmantv/cython/kalmantv.pxd
kalmantv/eigen/KalmanTV.h
kalmantv/eigen/KalmanTV.pxd
kalmantv/eigen/KalmanTV_raw.h
kalmantv/eigen/__init__.py
kalmantv/eigen/kalmantv.cp38-win_amd64.pyd
kalmantv/eigen/omp_init.cp38-win_amd64.pyd
kalmantv/jax/kalmantv.py
kalmantv/numba/__init__.py
kalmantv/numba/kalmantv.py
kalmantv/numba/scipy_linalg.py
kalmantv-0.2.4.9000.dist-info/METADATA
kalmantv-0.2.4.9000.dist-info/WHEEL
kalmantv-0.2.4.9000.dist-info/top_level.txt
kalmantv-0.2.4.9000.dist-info/RECORD
