Metadata-Version: 2.1
Name: kalmantv
Version: 0.2.4.9000
Summary: High-Performance Kalman Filtering and Smoothing
Home-page: http://github.com/mlysy/kalmantv
Author: Mohan Wu, Martin Lysy
Author-email: mlysy@uwaterloo.ca
License: UNKNOWN
Project-URL: Documentation, https://kalmantv.readthedocs.io/en/latest/
Keywords: Kalman Cython
Platform: UNKNOWN
Requires-Python: >=3.8
Requires-Dist: cython (>=0.29)
Requires-Dist: numpy (>=1.22)
Requires-Dist: scipy (>=1.2.1)
Requires-Dist: numba (>=0.51.2)
Requires-Dist: eigenpip
Provides-Extra: docs
Requires-Dist: sphinx ; extra == 'docs'
Requires-Dist: sphinx-rtd-theme ; extra == 'docs'
Requires-Dist: recommonmark ; extra == 'docs'
Provides-Extra: tests
Requires-Dist: pandas ; extra == 'tests'
Requires-Dist: tox ; extra == 'tests'
